MANIFEST.in
README.md
setup.py
lib/evernote/__init__.py
lib/evernote.egg-info/PKG-INFO
lib/evernote.egg-info/SOURCES.txt
lib/evernote.egg-info/dependency_links.txt
lib/evernote.egg-info/top_level.txt
lib/evernote/api/__init__.py
lib/evernote/api/client.py
lib/evernote/edam/__init__.py
lib/evernote/edam/error/__init__.py
lib/evernote/edam/error/constants.py
lib/evernote/edam/error/ttypes.py
lib/evernote/edam/limits/__init__.py
lib/evernote/edam/limits/constants.py
lib/evernote/edam/limits/ttypes.py
lib/evernote/edam/notestore/NoteStore.py
lib/evernote/edam/notestore/__init__.py
lib/evernote/edam/notestore/constants.py
lib/evernote/edam/notestore/ttypes.py
lib/evernote/edam/type/__init__.py
lib/evernote/edam/type/constants.py
lib/evernote/edam/type/ttypes.py
lib/evernote/edam/userstore/UserStore.py
lib/evernote/edam/userstore/__init__.py
lib/evernote/edam/userstore/constants.py
lib/evernote/edam/userstore/ttypes.py
lib/thrift/TSCons.py
lib/thrift/TSerialization.py
lib/thrift/Thrift.py
lib/thrift/__init__.py
lib/thrift/protocol/TBase.py
lib/thrift/protocol/TBinaryProtocol.py
lib/thrift/protocol/TCompactProtocol.py
lib/thrift/protocol/TProtocol.py
lib/thrift/protocol/__init__.py
lib/thrift/server/THttpServer.py
lib/thrift/server/TNonblockingServer.py
lib/thrift/server/TProcessPoolServer.py
lib/thrift/server/TServer.py
lib/thrift/server/__init__.py
lib/thrift/transport/THttpClient.py
lib/thrift/transport/TSSLSocket.py
lib/thrift/transport/TSocket.py
lib/thrift/transport/TTransport.py
lib/thrift/transport/TTwisted.py
lib/thrift/transport/TZlibTransport.py
lib/thrift/transport/__init__.py